audit_trails/__init__.py
audit_trails/admin.py
audit_trails/apps.py
audit_trails/logger.py
audit_trails/middleware.py
audit_trails/models.py
audit_trails/signals.py
audit_trails/tests.py
audit_trails/urls.py
audit_trails/views.py
audit_trails/api/__init__.py
audit_trails/api/serializers.py
audit_trails/api/urls.py
audit_trails/api/views.py
audit_trails/migrations/__init__.py
main/__init__.py
main/asgi.py
main/settings.py
main/urls.py
main/wsgi.py
afex_audit_trail-0.2.6.dist-info/LICENSE
afex_audit_trail-0.2.6.dist-info/METADATA
afex_audit_trail-0.2.6.dist-info/WHEEL
afex_audit_trail-0.2.6.dist-info/top_level.txt
afex_audit_trail-0.2.6.dist-info/RECORD
