Metadata-Version: 2.1
Name: afex-audit-trail
Version: 0.2.6
Summary: A Django app to create server logs and users' notification.
Home-page: UNKNOWN
Author: AFEX NIGERIA
Author-email: it@afexnigeria.com
License: MIT
Platform: UNKNOWN
Classifier: Framework :: Django
Classifier: Framework :: Django :: 4.0
Classifier: Intended Audience :: Developers
Classifier: License :: OSI Approved :: MIT License
Classifier: Operating System :: OS Independent
Classifier: Programming Language :: Python
Classifier: Programming Language :: Python :: 3
Classifier: Programming Language :: Python :: 3 :: Only
Classifier: Programming Language :: Python :: 3.8
Classifier: Programming Language :: Python :: 3.9
Classifier: Topic :: Internet :: WWW/HTTP
Classifier: Topic :: Internet :: WWW/HTTP :: Dynamic Content
Requires-Python: >=3.7
Requires-Dist: django (>=4.0)
Requires-Dist: djangorestframework (>=3.14)
Requires-Dist: djangorestframework-simplejwt (>=5.2)
